nonebot_plugin_minesweeper/__init__.py
nonebot_plugin_minesweeper/config.py
nonebot_plugin_minesweeper/data_source.py
nonebot_plugin_minesweeper/resources/fonts/00TT.TTF
nonebot_plugin_minesweeper/resources/skins/clone.bmp
nonebot_plugin_minesweeper/resources/skins/colorsonly.bmp
nonebot_plugin_minesweeper/resources/skins/hibbeler.bmp
nonebot_plugin_minesweeper/resources/skins/icicle.bmp
nonebot_plugin_minesweeper/resources/skins/mario.bmp
nonebot_plugin_minesweeper/resources/skins/maviz.bmp
nonebot_plugin_minesweeper/resources/skins/mine.bmp
nonebot_plugin_minesweeper/resources/skins/narkomania.bmp
nonebot_plugin_minesweeper/resources/skins/ocean.bmp
nonebot_plugin_minesweeper/resources/skins/pacman.bmp
nonebot_plugin_minesweeper/resources/skins/predator.bmp
nonebot_plugin_minesweeper/resources/skins/scratch.bmp
nonebot_plugin_minesweeper/resources/skins/symbol.bmp
nonebot_plugin_minesweeper/resources/skins/unknown.bmp
nonebot_plugin_minesweeper/resources/skins/vista.bmp
nonebot_plugin_minesweeper/resources/skins/win98.bmp
nonebot_plugin_minesweeper/resources/skins/winbw.bmp
nonebot_plugin_minesweeper/resources/skins/winxp.bmp
nonebot_plugin_minesweeper/utils.py
nonebot_plugin_minesweeper-0.4.2.dist-info/LICENSE
nonebot_plugin_minesweeper-0.4.2.dist-info/METADATA
nonebot_plugin_minesweeper-0.4.2.dist-info/WHEEL
nonebot_plugin_minesweeper-0.4.2.dist-info/RECORD
